HISTORY.rst
LICENSE.txt
MANIFEST.in
README.rst
setup.py
test_schedule.py
aioschedule/__init__.py
aioschedule.egg-info/PKG-INFO
aioschedule.egg-info/SOURCES.txt
aioschedule.egg-info/dependency_links.txt
aioschedule.egg-info/top_level.txt