Metadata-Version: 1.1
Name: aioschedule
Version: 0.5.0
Summary: Job scheduling for humans.
Home-page: https://github.com/ibrb/python-aioschedule
Author: Daniel Bader, Cochise Ruhulessin
Author-email: development@ibrb.io
License: MIT
Download-URL: https://github.com/ibrb/python-aioschedule/tarball/0.5.0
Keywords: aioschedule,periodic,jobs,scheduling,clockwork,cron,scheduler,job scheduling
Platform: UNKNOWN
Classifier: Intended Audience :: Developers
Classifier: License :: OSI Approved :: MIT License
Classifier: Programming Language :: Python
Classifier: Programming Language :: Python :: 3.5
Classifier: Programming Language :: Python :: 3.6
Classifier: Natural Language :: English
